{
  "project_info": {
    "project_number": "289355023106",
    "project_id": "uteethdentista",
    "storage_bucket": "uteethdentista.appspot.com"
  },
  "client": [
    {
      "client_info": {
        "mobilesdk_app_id": "1:289355023106:android:cf888b6c20cc2418f5b81b",
        "android_client_info": {
          "package_name": "br.edu.puc.uteethdentista"
        }
      },
      "oauth_client": [
        {
          "client_id": "289355023106-4ks4jdh27qgtabvp92cl24j4s1b13qv5.apps.googleusercontent.com",
          "client_type": 3
        }
      ],
      "api_key": [
        {
          "current_key": "AIzaSyCD-zlg7TYQk5CV-9aHGKWkq1CLHwpn688"
        }
      ],
      "services": {
        "appinvite_service": {
          "other_platform_oauth_client": [
            {
              "client_id": "289355023106-4ks4jdh27qgtabvp92cl24j4s1b13qv5.apps.googleusercontent.com",
              "client_type": 3
            }
          ]
        }
      }
    }
  ],
  "configuration_version": "1"
}